gmx_python_sdk/__init__.py
gmx_python_sdk/contracts/arbitrum/chainlinkdatastreamprovider.json
gmx_python_sdk/contracts/arbitrum/chainlinkpricefeedprovider.json
gmx_python_sdk/contracts/arbitrum/datastore.json
gmx_python_sdk/contracts/arbitrum/depositvault.json
gmx_python_sdk/contracts/arbitrum/eventemitter.json
gmx_python_sdk/contracts/arbitrum/exchangerouter.json
gmx_python_sdk/contracts/arbitrum/glvreader.json
gmx_python_sdk/contracts/arbitrum/gmoracleprovider.json
gmx_python_sdk/contracts/arbitrum/oracle.json
gmx_python_sdk/contracts/arbitrum/orderhandler.json
gmx_python_sdk/contracts/arbitrum/ordervault.json
gmx_python_sdk/contracts/arbitrum/syntheticsreader.json
gmx_python_sdk/contracts/arbitrum/syntheticsrouter.json
gmx_python_sdk/contracts/arbitrum/withdrawalvault.json
gmx_python_sdk/contracts/avalanche/datastore.json
gmx_python_sdk/contracts/avalanche/depositvault.json
gmx_python_sdk/contracts/avalanche/eventemitter.json
gmx_python_sdk/contracts/avalanche/exchangerouter.json
gmx_python_sdk/contracts/avalanche/glvreader.json
gmx_python_sdk/contracts/avalanche/ordervault.json
gmx_python_sdk/contracts/avalanche/syntheticsreader.json
gmx_python_sdk/contracts/avalanche/syntheticsrouter.json
gmx_python_sdk/contracts/avalanche/withdrawalvault.json
gmx_python_sdk/contracts/balance_abi.json
gmx_python_sdk/contracts/token_approval.json
gmx_python_sdk/data_store/placeholder.txt
gmx_python_sdk/scripts/__init__.py
gmx_python_sdk/scripts/v2/__init__.py
gmx_python_sdk/scripts/v2/approve_token_for_spend.py
gmx_python_sdk/scripts/v2/gas_utils.py
gmx_python_sdk/scripts/v2/get/get.py
gmx_python_sdk/scripts/v2/get/get_available_liquidity.py
gmx_python_sdk/scripts/v2/get/get_borrow_apr.py
gmx_python_sdk/scripts/v2/get/get_claimable_fees.py
gmx_python_sdk/scripts/v2/get/get_contract_balance.py
gmx_python_sdk/scripts/v2/get/get_funding_apr.py
gmx_python_sdk/scripts/v2/get/get_glv_stats.py
gmx_python_sdk/scripts/v2/get/get_gm_prices.py
gmx_python_sdk/scripts/v2/get/get_markets.py
gmx_python_ng-1.0.1.dist-info/LICENSE
gmx_python_ng-1.0.1.dist-info/METADATA
gmx_python_ng-1.0.1.dist-info/WHEEL
gmx_python_ng-1.0.1.dist-info/RECORD
