Metadata-Version: 2.3
Name: gmx-python-ng
Version: 1.0.1
Summary: A Python SDK for interacting with GMX
License: MIT
Author: snipermonke01
Author-email: snipermonke01@proton.me
Maintainer: Mikko Ohtamaa
Maintainer-email: mikko@tradingstrategy.ai
Requires-Python: >=3.10,<4
Classifier: License :: OSI Approved :: MIT License
Classifier: Programming Language :: Python :: 3
Classifier: Programming Language :: Python :: 3.10
Classifier: Programming Language :: Python :: 3.11
Classifier: Programming Language :: Python :: 3.12
Classifier: Programming Language :: Python :: 3.13
Requires-Dist: Packaging (>=24.1)
Requires-Dist: hexbytes (>=0.3.1)
Requires-Dist: numerize (>=0.12)
Requires-Dist: numpy (>=1.26.3)
Requires-Dist: pandas (>=1.4.2)
Requires-Dist: pyyaml (>=6.0.1)
Requires-Dist: ruff (>=0.11.6,<0.12.0)
Requires-Dist: web3 (>=6.10.0)
Project-URL: Changelog, https://github.com/tradingstrategy-ai/web3-ethereum-defi/blob/master/CHANGELOG.md
Project-URL: Documentation, https://web3-ethereum-defi.readthedocs.io/
Project-URL: Discord, https://discord.gg/5M88m9nM8H
Project-URL: Repository, https://github.com/tradingstrategy-ai/gmx-python-ng
Project-URL: Sponsor, https://tradingstrategy.ai
Project-URL: Twitter, https://twitter.com/tradingprotocol
Project-URL: Youtube, https://www.youtube.com/@tradingstrategyprotocol
